{
	"ident": 1016,
	"order": 1,
	"objtype": "kComponent",
	"componentlib": "OWrite",
	"componentctrl": "OWrite Window Object",
	"properties": {
		"::bottommargin": 2.54,
		"::leftmargin": 2.54,
		"::orientation": "kOrientPortrait",
		"::paper": "0",
		"::paperlength": 27.94,
		"::paperwidth": 21.59,
		"::rightmargin": 2.54,
		"::showrulers": false,
		"::topmargin": 2.54,
		"active": true,
		"align": "kLeftJst",
		"alpha": 255,
		"backcolor": "kGray",
		"backpattern": 0,
		"candropcursor": 0,
		"checkoverflow": true,
		"contextmenu": "",
		"convtoshared": true,
		"cursor": 0,
		"dataname": "",
		"datanametype": "kWriFmtUnassigned",
		"deftab": 1.27,
		"desgroup": 0,
		"designactive": true,
		"deslock": false,
		"disablefocus": false,
		"disablesystemfocus": false,
		"docscale": 100,
		"dragborder": false,
		"dragiconid": 0,
		"dragmode": "kNoDragging",
		"dragrange": "kRangeAll",
		"dropmode": "kAcceptNone",
		"edgefloat": "kEFnone",
		"effect": "kBorderInset",
		"enabled": true,
		"evalkeeplf": false,
		"evallocal": false,
		"fieldstyle": "",
		"firsttabiconid": 0,
		"font": 3,
		"fontsize": 14,
		"fontstyle": "kPlain",
		"forecolor": "kGray",
		"headfootenabled": true,
		"height": 228,
		"helpfile": 0,
		"horzscroll": false,
		"keyevents": false,
		"left": 30,
		"linktextcolor": "kBlue",
		"linktextstyle": "kUnderline",
		"maximagesize": 0,
		"mouseevents": false,
		"newprimeasure": false,
		"nobackground": false,
		"nocursor": false,
		"nodropcursor": 0,
		"nohilite": false,
		"nospellcheck": false,
		"notableoutline": false,
		"notabs": false,
		"nouserscroll": false,
		"objlink": 0,
		"pageview": "kWriViewField",
		"papercolor": "RGB(0,0,0)",
		"papercontinuous": false,
		"pasterawpicts": false,
		"printdpi": 600,
		"rmouseevents": false,
		"screendpi": "kWriScrDPI72",
		"showcms": true,
		"showinvisibles": false,
		"showprogress": false,
		"singlepagepreview": false,
		"spellinterval": 5,
		"statusevents": false,
		"stringcolumn": 0,
		"stringlist": "",
		"textcolor": "kColorWindowText",
		"tooltip": "",
		"top": 44,
		"userinfo": "",
		"vertscroll": false,
		"visible": true,
		"watermarks": "",
		"width": 267
	}
}
